i18n/__init__.py
i18n/config.py
i18n/resource_loader.py
i18n/translations.py
i18n/translator.py
i18n/loaders/__init__.py
i18n/loaders/json_loader.py
i18n/loaders/loader.py
i18n/loaders/python_loader.py
i18n/loaders/yaml_loader.py
i18n/tests/__init__.py
i18n/tests/loader_tests.py
i18n/tests/run_tests.py
i18n/tests/translation_tests.py
python_i18n-0.3.9.dist-info/LICENSE
python_i18n-0.3.9.dist-info/METADATA
python_i18n-0.3.9.dist-info/WHEEL
python_i18n-0.3.9.dist-info/top_level.txt
python_i18n-0.3.9.dist-info/zip-safe
python_i18n-0.3.9.dist-info/RECORD
