Metadata-Version: 2.1
Name: python-i18n
Version: 0.3.9
Summary: Translation library for Python
Home-page: https://github.com/tuvistavie/python-i18n
Author: Daniel Perez
Author-email: tuvistavie@gmail.com
License: MIT
Download-URL: https://github.com/tuvistavie/python-i18n/archive/master.zip
Platform: UNKNOWN
Classifier: Development Status :: 4 - Beta
Classifier: Environment :: Other Environment
Classifier: Intended Audience :: Developers
Classifier: License :: OSI Approved :: MIT License
Classifier: Operating System :: OS Independent
Classifier: Programming Language :: Python :: 2
Classifier: Programming Language :: Python :: 3
Classifier: Topic :: Software Development :: Libraries
Provides-Extra: YAML
